[
  {
    "type": "function",
    "name": "createSessionKey",
    "inputs": [
      {
        "name": "user",
        "type": "address",
        "internalType": "address"
      },
      {
        "name": "agentPubkey",
        "type": "bytes",
        "internalType": "bytes"
      },
      {
        "name": "durationSeconds",
        "type": "uint256",
        "internalType": "uint256"
      },
      {
        "name": "dailyLimitUsd",
        "type": "uint256",
        "internalType": "uint256"
      }
    ],
    "outputs": [
      {
        "name": "sessionId",
        "type": "bytes32",
        "internalType": "bytes32"
      }
    ],
    "stateMutability": "payable"
  },
  {
    "type": "function",
    "name": "getSession",
    "inputs": [
      {
        "name": "sessionId",
        "type": "bytes32",
        "internalType": "bytes32"
      }
    ],
    "outputs": [
      {
        "name": "user",
        "type": "address",
        "internalType": "address"
      },
      {
        "name": "expiryTimestamp",
        "type": "uint256",
        "internalType": "uint256"
      },
      {
        "name": "isActive",
        "type": "bool",
        "internalType": "bool"
      }
    ],
    "stateMutability": "view"
  },
  {
    "type": "function",
    "name": "keyToSessionId",
    "inputs": [
      {
        "name": "",
        "type": "address",
        "internalType": "address"
      }
    ],
    "outputs": [
      {
        "name": "",
        "type": "bytes32",
        "internalType": "bytes32"
      }
    ],
    "stateMutability": "view"
  },
  {
    "type": "function",
    "name": "renewSession",
    "inputs": [
      {
        "name": "user",
        "type": "address",
        "internalType": "address"
      },
      {
        "name": "sessionId",
        "type": "bytes32",
        "internalType": "bytes32"
      },
      {
        "name": "extendDuration",
        "type": "uint256",
        "internalType": "uint256"
      }
    ],
    "outputs": [],
    "stateMutability": "nonpayable"
  },
  {
    "type": "function",
    "name": "revokeSession",
    "inputs": [
      {
        "name": "user",
        "type": "address",
        "internalType": "address"
      },
      {
        "name": "sessionId",
        "type": "bytes32",
        "internalType": "bytes32"
      }
    ],
    "outputs": [],
    "stateMutability": "nonpayable"
  },
  {
    "type": "function",
    "name": "sessions",
    "inputs": [
      {
        "name": "",
        "type": "bytes32",
        "internalType": "bytes32"
      }
    ],
    "outputs": [
      {
        "name": "user",
        "type": "address",
        "internalType": "address"
      },
      {
        "name": "agentPubkey",
        "type": "bytes",
        "internalType": "bytes"
      },
      {
        "name": "expiryTimestamp",
        "type": "uint256",
        "internalType": "uint256"
      },
      {
        "name": "dailyLimitUsd",
        "type": "uint256",
        "internalType": "uint256"
      },
      {
        "name": "dailyUsedUsd",
        "type": "uint256",
        "internalType": "uint256"
      },
      {
        "name": "lastResetDay",
        "type": "uint256",
        "internalType": "uint256"
      },
      {
        "name": "isActive",
        "type": "bool",
        "internalType": "bool"
      },
      {
        "name": "autoRenewable",
        "type": "bool",
        "internalType": "bool"
      }
    ],
    "stateMutability": "view"
  },
  {
    "type": "function",
    "name": "updateDailySpending",
    "inputs": [
      {
        "name": "sessionId",
        "type": "bytes32",
        "internalType": "bytes32"
      },
      {
        "name": "amountUsd",
        "type": "uint256",
        "internalType": "uint256"
      }
    ],
    "outputs": [],
    "stateMutability": "nonpayable"
  },
  {
    "type": "function",
    "name": "validateSession",
    "inputs": [
      {
        "name": "sessionId",
        "type": "bytes32",
        "internalType": "bytes32"
      },
      {
        "name": "signature",
        "type": "bytes",
        "internalType": "bytes"
      }
    ],
    "outputs": [
      {
        "name": "",
        "type": "bool",
        "internalType": "bool"
      }
    ],
    "stateMutability": "view"
  },
  {
    "type": "function",
    "name": "validateSessionKey",
    "inputs": [
      {
        "name": "user",
        "type": "address",
        "internalType": "address"
      },
      {
        "name": "sessionKey",
        "type": "address",
        "internalType": "address"
      }
    ],
    "outputs": [
      {
        "name": "",
        "type": "bool",
        "internalType": "bool"
      }
    ],
    "stateMutability": "view"
  },
  {
    "type": "event",
    "name": "SessionCreated",
    "inputs": [
      {
        "name": "sessionId",
        "type": "bytes32",
        "indexed": true,
        "internalType": "bytes32"
      },
      {
        "name": "user",
        "type": "address",
        "indexed": true,
        "internalType": "address"
      },
      {
        "name": "expiryTimestamp",
        "type": "uint256",
        "indexed": false,
        "internalType": "uint256"
      }
    ],
    "anonymous": false
  },
  {
    "type": "event",
    "name": "SessionRenewed",
    "inputs": [
      {
        "name": "sessionId",
        "type": "bytes32",
        "indexed": true,
        "internalType": "bytes32"
      },
      {
        "name": "newExpiry",
        "type": "uint256",
        "indexed": false,
        "internalType": "uint256"
      }
    ],
    "anonymous": false
  },
  {
    "type": "event",
    "name": "SessionRevoked",
    "inputs": [
      {
        "name": "sessionId",
        "type": "bytes32",
        "indexed": true,
        "internalType": "bytes32"
      }
    ],
    "anonymous": false
  },
  {
    "type": "error",
    "name": "ECDSAInvalidSignature",
    "inputs": []
  },
  {
    "type": "error",
    "name": "ECDSAInvalidSignatureLength",
    "inputs": [
      {
        "name": "length",
        "type": "uint256",
        "internalType": "uint256"
      }
    ]
  },
  {
    "type": "error",
    "name": "ECDSAInvalidSignatureS",
    "inputs": [
      {
        "name": "s",
        "type": "bytes32",
        "internalType": "bytes32"
      }
    ]
  },
  {
    "type": "error",
    "name": "ExecutionFailed",
    "inputs": []
  },
  {
    "type": "error",
    "name": "SessionDailyLimitExceeded",
    "inputs": []
  },
  {
    "type": "error",
    "name": "SessionInactive",
    "inputs": []
  },
  {
    "type": "error",
    "name": "Unauthorized",
    "inputs": []
  }
]